reflex_global_hotkey/__init__.py
reflex_global_hotkey-1.2.3.dist-info/METADATA
reflex_global_hotkey-1.2.3.dist-info/WHEEL
reflex_global_hotkey-1.2.3.dist-info/RECORD
