Metadata-Version: 2.4
Name: reflex-global-hotkey
Version: 1.2.3
Summary: Global Hotkey Watcher for Reflex
Project-URL: repository, https://github.com/adhami3310/reflex-global-hotkey
Author-email: Khaleel Al-Adhami <khaleel.aladhami@gmail.com>
License: MIT
Keywords: reflex,reflex-custom-components
Requires-Python: >=3.10
Requires-Dist: reflex>=0.7.14
